rustymimi-0.4.0.dist-info/METADATA
rustymimi-0.4.0.dist-info/WHEEL
rustymimi.libs/libgcc_s-1e52349c.so.1
rustymimi/__init__.py
rustymimi/__init__.pyi
rustymimi/rustymimi.cpython-313-x86_64-linux-musl.so
rustymimi-0.4.0.dist-info/RECORD
